modelinfo/__init__.py
modelinfo/profiler.py
modelinfo-0.0.1.dist-info/METADATA
modelinfo-0.0.1.dist-info/WHEEL
modelinfo-0.0.1.dist-info/top_level.txt
modelinfo-0.0.1.dist-info/RECORD
