Metadata-Version: 2.4
Name: modelinfo
Version: 0.0.1
Summary: A Python library for model FLOPs and throughput benchmarking
Author: 17fine
Author-email: 17fine <2756601885@qq.com>
License: MIT
Classifier: Programming Language :: Python :: 3
Classifier: License :: OSI Approved :: MIT License
Classifier: Operating System :: OS Independent
Requires-Python: >=3.8
Requires-Dist: torch
Requires-Dist: torchvision
Requires-Dist: thop
Requires-Dist: torchinfo
Dynamic: author
Dynamic: requires-python
